{
  "project_info": {
    "project_number": "665832067549",
    "project_id": "sazashopping-ec7c2",
    "storage_bucket": "sazashopping-ec7c2.appspot.com"
  },
  "client": [
    {
      "client_info": {
        "mobilesdk_app_id": "1:665832067549:android:1373379cc6cc7d7cad6634",
        "android_client_info": {
          "package_name": "com.dissanayake.sazashopping"
        }
      },
      "oauth_client": [
        {
          "client_id": "665832067549-dfsr8d2kdsudr3vksinr4mtllt6lv89e.apps.googleusercontent.com",
          "client_type": 3
        }
      ],
      "api_key": [
        {
          "current_key": "AIzaSyBAVCXe__v4nBn8IMFHiC6hoewMYMNkto4"
        }
      ],
      "services": {
        "appinvite_service": {
          "other_platform_oauth_client": [
            {
              "client_id": "665832067549-dfsr8d2kdsudr3vksinr4mtllt6lv89e.apps.googleusercontent.com",
              "client_type": 3
            }
          ]
        }
      }
    }
  ],
  "configuration_version": "1"
}